pyenvrunner/__init__.py
pyenvrunner/cli/__init__.py
pyenvrunner/cli/main.py
pyenvrunner/core/__init__.py
pyenvrunner/core/config.py
pyenvrunner/core/exceptions.py
pyenvrunner/core/package_management.py
pyenvrunner/core/venv_management.py
pyenvrunner-1.0.0.dist-info/METADATA
pyenvrunner-1.0.0.dist-info/WHEEL
pyenvrunner-1.0.0.dist-info/entry_points.txt
pyenvrunner-1.0.0.dist-info/top_level.txt
pyenvrunner-1.0.0.dist-info/RECORD
