Metadata-Version: 2.4
Name: pyenvrunner
Version: 1.0.0
Summary: Wrapper to manage Python venvs & run scripts, installing missing dependencies
Home-page: https://github.com/yourusername/pyenvrunner
Author: Aditya Thiyyagura
Author-email: thiyyaguraadityareddy@gmail.com
License: MIT
Project-URL: Bug Reports, https://github.com/yourusername/pyenvrunner/issues
Project-URL: Source, https://github.com/yourusername/pyenvrunner
Keywords: venv virtualenv dependency-management pip automation
Classifier: Development Status :: 3 - Alpha
Classifier: Intended Audience :: Developers
Classifier: License :: OSI Approved :: MIT License
Classifier: Programming Language :: Python :: 3
Classifier: Programming Language :: Python :: 3.6
Classifier: Programming Language :: Python :: 3.7
Classifier: Programming Language :: Python :: 3.8
Classifier: Programming Language :: Python :: 3.9
Classifier: Programming Language :: Python :: 3.10
Classifier: Programming Language :: Python :: 3.11
Classifier: Topic :: Software Development :: Libraries :: Python Modules
Classifier: Topic :: System :: Installation/Setup
Requires-Python: >=3.6
Dynamic: author
Dynamic: author-email
Dynamic: classifier
Dynamic: description
Dynamic: description-content-type
Dynamic: home-page
Dynamic: keywords
Dynamic: license
Dynamic: project-url
Dynamic: requires-python
Dynamic: summary
